{
  "Earn With Your Smartphone":"censorship",
  "Earn With Your Smartphone":"censorship",
"Trading Mistakes":"grapes",
"Promote Your Business":"keyboard",
"Offering Pet Care Services":"sanyo",
"Myths About Making Money":"about",
"Make Money with Customizable Tech Gadgets":"gadgets",
"TikTok Shop Dropshipping":"holland",
"Create a Successful Business Plan":"pending",
"It's Time to Quit Your 9 to 5 Job":"views",
"Mistakes New Entrepreneurs Make":"mistake",
"Professions That Pay Well":"linktg",
"Affiliate Marketing With AI":"lemonade",
"Instagram Reels VIRAL":"monitor",
"Multiple Income Streams":"universal",
"Save Money While Traveling":"ideas3",
"Business Ideas for Students":"google",
"$500/Day with Google Search":"student",
"Outsource Effectively":"owner",
"Use LinkedIn to Grow":"career",
"Spoiler Alert Who Is Satoshi? | Part 1":"K&(9)",
"Spoiler Alert Who Is Satoshi? | Part 2":"6A3=H",
"Stay Productive as a Solopreneur":"mistakes"

}
